teladduser/__init__.py
teladduser/teladduser.py
teladduser-0.1.0.dist-info/entry_points.txt
teladduser-0.1.0.dist-info/LICENSE
teladduser-0.1.0.dist-info/WHEEL
teladduser-0.1.0.dist-info/METADATA
teladduser-0.1.0.dist-info/RECORD
